{
  "$schema": "https://buildy.tw/schema/registry.json",
  "items": [
    {
      "name": "button",
      "type": "registry:ui",
      "dependencies": [
        "react"
      ],
      "devDependencies": [],
      "files": [
        {
          "path": "packages/ui/src/ui/button.tsx",
          "target": "ui"
        }
      ]
    },
    {
      "name": "utils",
      "type": "registry:lib",
      "dependencies": [
        "clsx",
        "tailwind-merge"
      ],
      "devDependencies": [],
      "files": [
        {
          "path": "packages/ui/src/lib/utils.ts",
          "target": "lib"
        }
      ]
    },
    {
      "name": "hero-section",
      "type": "registry:block",
      "dependencies": [
        "react"
      ],
      "devDependencies": [],
      "files": [
        {
          "path": "packages/ui/src/blocks/hero-section.tsx",
          "target": "blocks"
        }
      ]
    }
  ]
}